da_lib/__init__.py
da_lib/saudacao.py
da_lib/connections/__init__.py
da_lib/connections/connect.py
da_lib/gcp/__init__.py
da_lib/gcp/bigquery.py
da_lib/gcp/storage.py
da_lib/monitoring/__init__.py
da_lib/monitoring/bqfuntions.py
da_lib/monitoring/ingestion.py
da_lib/transform/__init__.py
da_lib/transform/files.py
da_lib/transform/transformation.py
da_template_lib-0.0.30.dist-info/LICENSE
da_template_lib-0.0.30.dist-info/METADATA
da_template_lib-0.0.30.dist-info/WHEEL
da_template_lib-0.0.30.dist-info/top_level.txt
da_template_lib-0.0.30.dist-info/RECORD
