Metadata-Version: 2.2
Name: da-template-lib
Version: 0.0.30
Summary: Template squad Inovação em Dados
Author: Kaue Matheus Santana
Author-email: kaue.santana@equifax.com
License: MIT License
Keywords: Template Inovação em Dados
License-File: LICENSE
Requires-Dist: google-cloud-storage
Requires-Dist: google-cloud-bigquery
Requires-Dist: unicode
Requires-Dist: pandas
Dynamic: author
Dynamic: author-email
Dynamic: description
Dynamic: description-content-type
Dynamic: keywords
Dynamic: license
Dynamic: requires-dist
Dynamic: summary
